MultiTerm_killgriff22/__init__.py
MultiTerm_killgriff22/classes.py
MultiTerm_killgriff22/modules.py
MultiTerm_killgriff22-1.0.0.dist-info/LICENSE
MultiTerm_killgriff22-1.0.0.dist-info/METADATA
MultiTerm_killgriff22-1.0.0.dist-info/WHEEL
MultiTerm_killgriff22-1.0.0.dist-info/top_level.txt
MultiTerm_killgriff22-1.0.0.dist-info/RECORD
