Metadata-Version: 2.1
Name: MultiTerm_killgriff22
Version: 1.0.0
Summary: A package to let you split your terminal into multiple sections, each independent of the other.
Author-email: killgriff22 <author@example.com>
Project-URL: Homepage, https://github.com/killgriff22/MultiTerm
Project-URL: Issues, https://github.com/killgriff22/MultiTerm/issues
Classifier: Programming Language :: Python :: 3
Classifier: License :: OSI Approved :: MIT License
Classifier: Operating System :: OS Independent
Requires-Python: >=3.8
License-File: LICENSE
